sola_python_utils/common/__init__.py
sola_python_utils/common/line_notify.py
sola_python_utils/common/memory_usage.py
sola_python_utils/common/system_command.py
sola_python_utils/common/template.py
sola_python_utils/readme.py
sola_python_utils-0.1.2.dist-info/METADATA
sola_python_utils-0.1.2.dist-info/WHEEL
sola_python_utils-0.1.2.dist-info/RECORD
