Metadata-Version: 2.1
Name: sola-python-utils
Version: 0.1.2
Summary: python utils for s-hirano-ist
Home-page: https://github.com/s-hirano-ist/sola-python-utils#readme
Author: s-hirano-ist
Author-email: s-hirano-ist@outlook.com
Requires-Python: >=3.11.4,<4.0.0
Classifier: Programming Language :: Python :: 3
Classifier: Programming Language :: Python :: 3.12
Requires-Dist: python-dotenv (>=1.0.0,<2.0.0)
Requires-Dist: requests (>=2.31.0,<3.0.0)
Project-URL: Repository, https://github.com/s-hirano-ist/sola-python-utils
